fluxmq/__init__.py
fluxmq/message.py
fluxmq/status.py
fluxmq/topic.py
fluxmq/transport.py
fluxmq/adapter/__init__.py
fluxmq/adapter/mqtt.py
fluxmq/adapter/nats.py
fluxmq/adapter/zenoh.py
fluxmq-0.15.0.dist-info/LICENSE
fluxmq-0.15.0.dist-info/METADATA
fluxmq-0.15.0.dist-info/WHEEL
fluxmq-0.15.0.dist-info/top_level.txt
fluxmq-0.15.0.dist-info/RECORD
