Metadata-Version: 2.1
Name: fluxmq
Version: 0.15.0
Summary: FluxMQ for Python
Home-page: https://github.com/flux/fluxmq-py
Author: Eugene Zimnitskiy
Author-email: karpotkin@gmail.com
License: UNKNOWN
Platform: UNKNOWN
Classifier: Development Status :: 3 - Alpha
Classifier: Intended Audience :: Developers
Classifier: License :: OSI Approved :: MIT License
Classifier: Programming Language :: Python :: 3
Classifier: Programming Language :: Python :: 3.7
Classifier: Programming Language :: Python :: 3.8
Classifier: Programming Language :: Python :: 3.9
Classifier: Programming Language :: Python :: 3.10
Classifier: Programming Language :: Python :: 3.11
Requires-Python: >=3.6
Requires-Dist: nats-py>=2.2.0
Requires-Dist: paho-mqtt>=2.0.0
Provides-Extra: all
Requires-Dist: zenoh>=0.7.0; extra == "all"
Provides-Extra: dev
Requires-Dist: pytest>=7.0.0; extra == "dev"
Requires-Dist: pytest-asyncio>=0.20.0; extra == "dev"
Requires-Dist: black>=23.0.0; extra == "dev"
Requires-Dist: isort>=5.12.0; extra == "dev"
Requires-Dist: mypy>=1.0.0; extra == "dev"
Provides-Extra: zenoh
Requires-Dist: zenoh>=0.7.0; extra == "zenoh"
